pysecoda/__init__.py
pysecoda/api_client.py
pysecoda/pysecoda.py
pysecoda/endpoints/__init__.py
pysecoda/endpoints/charts.py
pysecoda/endpoints/collections.py
pysecoda/endpoints/columns.py
pysecoda/endpoints/custom_properties.py
pysecoda/endpoints/dashboards.py
pysecoda/endpoints/databases.py
pysecoda/endpoints/documents.py
pysecoda/endpoints/events.py
pysecoda/endpoints/glossary.py
pysecoda/endpoints/groups.py
pysecoda/endpoints/integrations.py
pysecoda/endpoints/lineage.py
pysecoda/endpoints/monitors.py
pysecoda/endpoints/queries.py
pysecoda/endpoints/questions.py
pysecoda/endpoints/resources.py
pysecoda/endpoints/schemas.py
pysecoda/endpoints/tables.py
pysecoda/endpoints/tags.py
pysecoda/endpoints/teams.py
pysecoda/endpoints/users.py
pysecoda-0.1.2.dist-info/LICENSE
pysecoda-0.1.2.dist-info/METADATA
pysecoda-0.1.2.dist-info/WHEEL
pysecoda-0.1.2.dist-info/top_level.txt
pysecoda-0.1.2.dist-info/RECORD
