Metadata-Version: 2.2
Name: pysecoda
Version: 0.1.2
Summary: Python API wrapper for the Secoda data platform
Home-page: https://github.com/matts52/pysecoda
Author: Matthew Senick
Author-email: senick.matthew@gmail.com
License: MIT License
Keywords: API wrapper Secoda data
Classifier: Development Status :: 3 - Alpha
Classifier: Intended Audience :: Developers
Classifier: Programming Language :: Python
License-File: LICENSE
Requires-Dist: requests
Dynamic: author
Dynamic: author-email
Dynamic: classifier
Dynamic: description
Dynamic: description-content-type
Dynamic: home-page
Dynamic: keywords
Dynamic: license
Dynamic: requires-dist
Dynamic: summary
